s3impleclient/__init__.py
s3impleclient/cli.py
s3impleclient/patcher.py
s3impleclient/progress.py
s3impleclient/download/__init__.py
s3impleclient/download/api.py
s3impleclient/download/config.py
s3impleclient/download/core.py
s3impleclient/download/result.py
s3impleclient/upload/__init__.py
s3impleclient/upload/api.py
s3impleclient/upload/config.py
s3impleclient/upload/core.py
s3impleclient/upload/result.py
s3impleclient-0.0.1.dist-info/licenses/LICENSE
s3impleclient-0.0.1.dist-info/METADATA
s3impleclient-0.0.1.dist-info/WHEEL
s3impleclient-0.0.1.dist-info/entry_points.txt
s3impleclient-0.0.1.dist-info/top_level.txt
s3impleclient-0.0.1.dist-info/RECORD
