Metadata-Version: 2.4
Name: S3impleClient
Version: 0.0.1
Summary: A simple, fast, and robust async S3/HTTP downloader with parallel range requests.
Author-email: "Shih-Ying Yeh(KohakuBlueLeaf)" <apolloyeh0123@gmail.com>
License: Apache-2.0
Project-URL: Homepage, https://github.com/KohakuBlueleaf/S3impleClient
Keywords: s3,download,async,parallel,huggingface
Classifier: Development Status :: 3 - Alpha
Classifier: Intended Audience :: Developers
Classifier: License :: OSI Approved :: Apache Software License
Classifier: Programming Language :: Python :: 3
Classifier: Programming Language :: Python :: 3.10
Classifier: Programming Language :: Python :: 3.11
Classifier: Programming Language :: Python :: 3.12
Classifier: Topic :: Internet :: WWW/HTTP
Classifier: Topic :: Software Development :: Libraries :: Python Modules
Requires-Python: >=3.10
License-File: LICENSE
Requires-Dist: httpx>=0.24.0
Requires-Dist: tqdm>=4.60.0
Requires-Dist: aiofiles>=25.0.0
Provides-Extra: dev
Requires-Dist: pytest>=9.0.0; extra == "dev"
Requires-Dist: pytest-asyncio>=1.3.0; extra == "dev"
Provides-Extra: jupyter
Requires-Dist: nest_asyncio>=1.5.0; extra == "jupyter"
Provides-Extra: hf
Requires-Dist: huggingface_hub>=1.0.0; extra == "hf"
Provides-Extra: all
Requires-Dist: S3impleClient[dev,hf,jupyter]; extra == "all"
Dynamic: license-file
